twitter_banner_switcher/__init__.py
twitter_banner_switcher/command_line.py
twitter_banner_switcher-0.1.0.data/scripts/twitter-banner-switcher
twitter_banner_switcher-0.1.0.dist-info/DESCRIPTION.rst
twitter_banner_switcher-0.1.0.dist-info/METADATA
twitter_banner_switcher-0.1.0.dist-info/RECORD
twitter_banner_switcher-0.1.0.dist-info/WHEEL
twitter_banner_switcher-0.1.0.dist-info/metadata.json
twitter_banner_switcher-0.1.0.dist-info/top_level.txt
