Metadata-Version: 2.0
Name: twitter-banner-switcher
Version: 0.1.0
Summary: Python script that sets your Twitter profile banner to a random image from a specified folder or a list of paths.
Home-page: https://github.com/Pythonity/twitter-banner-switcher
Author: Paweł Adamczak
Author-email: pawel.adamczak@sidnet.info
License: MIT License
Download-URL: https://github.com/Pythonity/twitter-banner-switcher/releases/latest
Keywords: twitter banner
Platform: UNKNOWN
Classifier: Development Status :: 4 - Beta
Classifier: Environment :: Console
Classifier: Intended Audience :: End Users/Desktop
Classifier: License :: OSI Approved :: MIT License
Classifier: Operating System :: OS Independent
Classifier: Programming Language :: Python
Classifier: Programming Language :: Python :: 3
Classifier: Programming Language :: Python :: 3.4
Classifier: Topic :: Utilities
Requires-Dist: PyYAML (>=3.11)
Requires-Dist: click (>=6.6)
Requires-Dist: tweepy (>=3.5.0)
